odoo/addons/shopinvader_sale_packaging_wishlist/README.rst
odoo/addons/shopinvader_sale_packaging_wishlist/__init__.py
odoo/addons/shopinvader_sale_packaging_wishlist/__manifest__.py
odoo/addons/shopinvader_sale_packaging_wishlist/i18n/shopinvader_sale_packaging_wishlist.pot
odoo/addons/shopinvader_sale_packaging_wishlist/readme/CONTRIBUTORS.rst
odoo/addons/shopinvader_sale_packaging_wishlist/readme/CREDITS.rst
odoo/addons/shopinvader_sale_packaging_wishlist/readme/DESCRIPTION.rst
odoo/addons/shopinvader_sale_packaging_wishlist/services/__init__.py
odoo/addons/shopinvader_sale_packaging_wishlist/services/wishlist.py
odoo/addons/shopinvader_sale_packaging_wishlist/static/description/icon.png
odoo/addons/shopinvader_sale_packaging_wishlist/static/description/index.html
odoo/addons/shopinvader_sale_packaging_wishlist/tests/__init__.py
odoo/addons/shopinvader_sale_packaging_wishlist/tests/test_wishlist_packaging.py
odoo13_addon_shopinvader_sale_packaging_wishlist-13.0.2.2.0.dist-info/METADATA
odoo13_addon_shopinvader_sale_packaging_wishlist-13.0.2.2.0.dist-info/WHEEL
odoo13_addon_shopinvader_sale_packaging_wishlist-13.0.2.2.0.dist-info/top_level.txt
odoo13_addon_shopinvader_sale_packaging_wishlist-13.0.2.2.0.dist-info/RECORD
