Metadata-Version: 2.1
Name: odoo13-addon-shopinvader-sale-packaging-wishlist
Version: 13.0.2.2.0
Summary: Add packaging information to wishlists
Home-page: https://github.com/shopinvader/odoo-shopinvader
Author: Camptocamp,Odoo Community Association (OCA)
Author-email: support@odoo-community.org
License: AGPL-3
Platform: UNKNOWN
Classifier: Programming Language :: Python
Classifier: Framework :: Odoo
Classifier: License :: OSI Approved :: GNU Affero General Public License v3
Requires-Python: >=3.5
Requires-Dist: odoo13-addon-sale-product-set-packaging-qty
Requires-Dist: odoo13-addon-shopinvader-sale-packaging
Requires-Dist: odoo13-addon-shopinvader-wishlist
Requires-Dist: odoo (<13.1dev,>=13.0a)
